TMDBTraktSyncer/TMDBTraktSyncer.py
TMDBTraktSyncer/__init__.py
TMDBTraktSyncer/__main__.py
TMDBTraktSyncer/arguments.py
TMDBTraktSyncer/authTrakt.py
TMDBTraktSyncer/checkVersion.py
TMDBTraktSyncer/errorHandling.py
TMDBTraktSyncer/errorLogger.py
TMDBTraktSyncer/tmdbData.py
TMDBTraktSyncer/traktData.py
TMDBTraktSyncer/verifyCredentials.py
tmdbtraktsyncer-2.3.0.dist-info/licenses/LICENSE
tmdbtraktsyncer-2.3.0.dist-info/METADATA
tmdbtraktsyncer-2.3.0.dist-info/WHEEL
tmdbtraktsyncer-2.3.0.dist-info/entry_points.txt
tmdbtraktsyncer-2.3.0.dist-info/top_level.txt
tmdbtraktsyncer-2.3.0.dist-info/RECORD
