Metadata-Version: 2.4
Name: TMDBTraktSyncer
Version: 2.3.0
Summary: A python script that syncs user watchlist and ratings for Movies, TV Shows and Episodes both ways between Trakt and TMDB.
Author: RileyXX
License: MIT License
Project-URL: homepage, https://github.com/RileyXX/TMDB-Trakt-Syncer
Project-URL: issues, https://github.com/RileyXX/TMDB-Trakt-Syncer/issues
Project-URL: changelog, https://github.com/RileyXX/TMDB-Trakt-Syncer/releases
Project-URL: funding, https://github.com/sponsors/RileyXX
Project-URL: repository, https://github.com/RileyXX/TMDB-Trakt-Syncer
Project-URL: documentation, https://github.com/RileyXX/TMDB-Trakt-Syncer
Classifier: Development Status :: 5 - Production/Stable
Classifier: Environment :: Console
Classifier: Operating System :: OS Independent
Classifier: License :: OSI Approved :: MIT License
Classifier: Programming Language :: Python :: 3
Requires-Python: >=3.6
License-File: LICENSE
Requires-Dist: requests>=2.32.3
Requires-Dist: selenium>=4.15.2
Dynamic: license-file
